pushed/__init__.py
pushed/pushed.py
pushed-0.1.4.dist-info/top_level.txt
pushed-0.1.4.dist-info/METADATA
pushed-0.1.4.dist-info/DESCRIPTION.rst
pushed-0.1.4.dist-info/metadata.json
pushed-0.1.4.dist-info/WHEEL
pushed-0.1.4.dist-info/RECORD
