Metadata-Version: 2.0
Name: pushed
Version: 0.1.4
Summary: Unofficial Pushed.co API wrapper
Home-page: https://github.com/digmore/pypushed/
Author: Duncan Gilmore
Author-email: pypi@digmore.tech
License: MIT
Keywords: pushed,pushed.co,mobile,apns,ios,apple,android
Platform: UNKNOWN
Classifier: Development Status :: 3 - Alpha
Classifier: Intended Audience :: Developers
Classifier: License :: OSI Approved :: MIT License
Classifier: Programming Language :: Python :: 2.6
Classifier: Programming Language :: Python :: 2.7
Classifier: Programming Language :: Python :: 3
Classifier: Programming Language :: Python :: 3.2
Classifier: Programming Language :: Python :: 3.3
Classifier: Programming Language :: Python :: 3.4
Requires-Dist: requests
